[
    {
        "quiz_session_id": 1,
        "sno": 1,
        "question_id": 1,
        "original_question": "<p>What is the charge of an electron?</p>",
        "options": "a:2:{i:0;s:15:\"<p>Positive</p>\";i:1;s:15:\"<p>Negative</p>\";}",
        "user_answer": "N;",
        "correct_answer": "i:2;",
        "status": "not_answered",
        "is_correct": 0,
        "time_taken": 23,
        "marks_earned": 0,
        "marks_deducted": 0
    },
    {
        "quiz_session_id": 1,
        "sno": 2,
        "question_id": 2,
        "original_question": "<p>What is the order of fundamental forces in nature according to their strengths.</p>",
        "options": "a:2:{s:7:\"matches\";a:4:{i:0;a:2:{s:2:\"id\";s:32:\"c215fc75951b35c5847a807240fab2ea\";s:5:\"value\";s:20:\"<p>Nuclear Force</p>\";}i:1;a:2:{s:2:\"id\";s:32:\"a9577d25b70d4788551133ae4f265347\";s:5:\"value\";s:27:\"<p>Electomagnetic Force</p>\";}i:2;a:2:{s:2:\"id\";s:32:\"2577539023dcd204eb78a3ad1cd6201c\";s:5:\"value\";s:25:\"<p>Weak Nuclear Force</p>\";}i:3;a:2:{s:2:\"id\";s:32:\"19be0e556de5c94f431c8d9ced56641f\";s:5:\"value\";s:26:\"<p>Gravitational Force</p>\";}}s:5:\"pairs\";a:4:{i:0;a:3:{s:2:\"id\";s:32:\"a22d6a95d33b5208f04eedb325282800\";s:5:\"value\";s:8:\"<p>1</p>\";s:4:\"code\";s:1:\"A\";}i:1;a:3:{s:2:\"id\";s:32:\"d1a89b1335613b7b84b5426e0ef6452a\";s:5:\"value\";s:8:\"<p>2</p>\";s:4:\"code\";s:1:\"B\";}i:2;a:3:{s:2:\"id\";s:32:\"7667e2cd947e57f259549e120bbc619d\";s:5:\"value\";s:8:\"<p>4</p>\";s:4:\"code\";s:1:\"C\";}i:3;a:3:{s:2:\"id\";s:32:\"1d996b61ee20735a967752c065fd62b0\";s:5:\"value\";s:8:\"<p>3</p>\";s:4:\"code\";s:1:\"D\";}}}",
        "user_answer": null,
        "correct_answer": "a:4:{i:0;s:32:\"a22d6a95d33b5208f04eedb325282800\";i:1;s:32:\"d1a89b1335613b7b84b5426e0ef6452a\";i:2;s:32:\"1d996b61ee20735a967752c065fd62b0\";i:3;s:32:\"7667e2cd947e57f259549e120bbc619d\";}",
        "status": "not_visited",
        "is_correct": null,
        "time_taken": 0,
        "marks_earned": 0,
        "marks_deducted": 0
    },
    {
        "quiz_session_id": 2,
        "sno": 1,
        "question_id": 1,
        "original_question": "<p>What is the charge of an electron?</p>",
        "options": "a:2:{i:0;s:15:\"<p>Positive</p>\";i:1;s:15:\"<p>Negative</p>\";}",
        "user_answer": "N;",
        "correct_answer": "i:2;",
        "status": "not_answered",
        "is_correct": 0,
        "time_taken": 272,
        "marks_earned": 0,
        "marks_deducted": 0
    },
    {
        "quiz_session_id": 2,
        "sno": 2,
        "question_id": 2,
        "original_question": "<p>What is the order of fundamental forces in nature according to their strengths.</p>",
        "options": "a:2:{s:7:\"matches\";a:4:{i:0;a:2:{s:2:\"id\";s:32:\"c215fc75951b35c5847a807240fab2ea\";s:5:\"value\";s:20:\"<p>Nuclear Force</p>\";}i:1;a:2:{s:2:\"id\";s:32:\"a9577d25b70d4788551133ae4f265347\";s:5:\"value\";s:27:\"<p>Electomagnetic Force</p>\";}i:2;a:2:{s:2:\"id\";s:32:\"2577539023dcd204eb78a3ad1cd6201c\";s:5:\"value\";s:25:\"<p>Weak Nuclear Force</p>\";}i:3;a:2:{s:2:\"id\";s:32:\"19be0e556de5c94f431c8d9ced56641f\";s:5:\"value\";s:26:\"<p>Gravitational Force</p>\";}}s:5:\"pairs\";a:4:{i:0;a:3:{s:2:\"id\";s:32:\"d1a89b1335613b7b84b5426e0ef6452a\";s:5:\"value\";s:8:\"<p>2</p>\";s:4:\"code\";s:1:\"A\";}i:1;a:3:{s:2:\"id\";s:32:\"7667e2cd947e57f259549e120bbc619d\";s:5:\"value\";s:8:\"<p>4</p>\";s:4:\"code\";s:1:\"B\";}i:2;a:3:{s:2:\"id\";s:32:\"1d996b61ee20735a967752c065fd62b0\";s:5:\"value\";s:8:\"<p>3</p>\";s:4:\"code\";s:1:\"C\";}i:3;a:3:{s:2:\"id\";s:32:\"a22d6a95d33b5208f04eedb325282800\";s:5:\"value\";s:8:\"<p>1</p>\";s:4:\"code\";s:1:\"D\";}}}",
        "user_answer": "a:0:{}",
        "correct_answer": "a:4:{i:0;s:32:\"a22d6a95d33b5208f04eedb325282800\";i:1;s:32:\"d1a89b1335613b7b84b5426e0ef6452a\";i:2;s:32:\"1d996b61ee20735a967752c065fd62b0\";i:3;s:32:\"7667e2cd947e57f259549e120bbc619d\";}",
        "status": "not_answered",
        "is_correct": 0,
        "time_taken": 1,
        "marks_earned": 0,
        "marks_deducted": 0
    },
    {
        "quiz_session_id": 3,
        "sno": 2,
        "question_id": 1,
        "original_question": "<p>What is the charge of an electron?</p>",
        "options": "a:2:{i:0;s:15:\"<p>Positive</p>\";i:1;s:15:\"<p>Negative</p>\";}",
        "user_answer": null,
        "correct_answer": "i:2;",
        "status": "not_visited",
        "is_correct": null,
        "time_taken": 0,
        "marks_earned": 0,
        "marks_deducted": 0
    },
    {
        "quiz_session_id": 3,
        "sno": 1,
        "question_id": 2,
        "original_question": "<p>What is the order of fundamental forces in nature according to their strengths.</p>",
        "options": "a:2:{s:7:\"matches\";a:4:{i:0;a:2:{s:2:\"id\";s:32:\"c215fc75951b35c5847a807240fab2ea\";s:5:\"value\";s:20:\"<p>Nuclear Force</p>\";}i:1;a:2:{s:2:\"id\";s:32:\"a9577d25b70d4788551133ae4f265347\";s:5:\"value\";s:27:\"<p>Electomagnetic Force</p>\";}i:2;a:2:{s:2:\"id\";s:32:\"2577539023dcd204eb78a3ad1cd6201c\";s:5:\"value\";s:25:\"<p>Weak Nuclear Force</p>\";}i:3;a:2:{s:2:\"id\";s:32:\"19be0e556de5c94f431c8d9ced56641f\";s:5:\"value\";s:26:\"<p>Gravitational Force</p>\";}}s:5:\"pairs\";a:4:{i:0;a:3:{s:2:\"id\";s:32:\"d1a89b1335613b7b84b5426e0ef6452a\";s:5:\"value\";s:8:\"<p>2</p>\";s:4:\"code\";s:1:\"A\";}i:1;a:3:{s:2:\"id\";s:32:\"a22d6a95d33b5208f04eedb325282800\";s:5:\"value\";s:8:\"<p>1</p>\";s:4:\"code\";s:1:\"B\";}i:2;a:3:{s:2:\"id\";s:32:\"1d996b61ee20735a967752c065fd62b0\";s:5:\"value\";s:8:\"<p>3</p>\";s:4:\"code\";s:1:\"C\";}i:3;a:3:{s:2:\"id\";s:32:\"7667e2cd947e57f259549e120bbc619d\";s:5:\"value\";s:8:\"<p>4</p>\";s:4:\"code\";s:1:\"D\";}}}",
        "user_answer": "a:0:{}",
        "correct_answer": "a:4:{i:0;s:32:\"a22d6a95d33b5208f04eedb325282800\";i:1;s:32:\"d1a89b1335613b7b84b5426e0ef6452a\";i:2;s:32:\"1d996b61ee20735a967752c065fd62b0\";i:3;s:32:\"7667e2cd947e57f259549e120bbc619d\";}",
        "status": "not_answered",
        "is_correct": 0,
        "time_taken": 28,
        "marks_earned": 0,
        "marks_deducted": 0
    },
    {
        "quiz_session_id": 4,
        "sno": 1,
        "question_id": 1,
        "original_question": "<p>What is the charge of an electron?</p>",
        "options": "a:2:{i:0;s:15:\"<p>Positive</p>\";i:1;s:15:\"<p>Negative</p>\";}",
        "user_answer": null,
        "correct_answer": "i:2;",
        "status": "not_visited",
        "is_correct": null,
        "time_taken": 0,
        "marks_earned": 0,
        "marks_deducted": 0
    },
    {
        "quiz_session_id": 4,
        "sno": 2,
        "question_id": 2,
        "original_question": "<p>What is the order of fundamental forces in nature according to their strengths.</p>",
        "options": "a:2:{s:7:\"matches\";a:4:{i:0;a:2:{s:2:\"id\";s:32:\"c215fc75951b35c5847a807240fab2ea\";s:5:\"value\";s:20:\"<p>Nuclear Force</p>\";}i:1;a:2:{s:2:\"id\";s:32:\"a9577d25b70d4788551133ae4f265347\";s:5:\"value\";s:27:\"<p>Electomagnetic Force</p>\";}i:2;a:2:{s:2:\"id\";s:32:\"2577539023dcd204eb78a3ad1cd6201c\";s:5:\"value\";s:25:\"<p>Weak Nuclear Force</p>\";}i:3;a:2:{s:2:\"id\";s:32:\"19be0e556de5c94f431c8d9ced56641f\";s:5:\"value\";s:26:\"<p>Gravitational Force</p>\";}}s:5:\"pairs\";a:4:{i:0;a:3:{s:2:\"id\";s:32:\"7667e2cd947e57f259549e120bbc619d\";s:5:\"value\";s:8:\"<p>4</p>\";s:4:\"code\";s:1:\"A\";}i:1;a:3:{s:2:\"id\";s:32:\"d1a89b1335613b7b84b5426e0ef6452a\";s:5:\"value\";s:8:\"<p>2</p>\";s:4:\"code\";s:1:\"B\";}i:2;a:3:{s:2:\"id\";s:32:\"a22d6a95d33b5208f04eedb325282800\";s:5:\"value\";s:8:\"<p>1</p>\";s:4:\"code\";s:1:\"C\";}i:3;a:3:{s:2:\"id\";s:32:\"1d996b61ee20735a967752c065fd62b0\";s:5:\"value\";s:8:\"<p>3</p>\";s:4:\"code\";s:1:\"D\";}}}",
        "user_answer": null,
        "correct_answer": "a:4:{i:0;s:32:\"a22d6a95d33b5208f04eedb325282800\";i:1;s:32:\"d1a89b1335613b7b84b5426e0ef6452a\";i:2;s:32:\"1d996b61ee20735a967752c065fd62b0\";i:3;s:32:\"7667e2cd947e57f259549e120bbc619d\";}",
        "status": "not_visited",
        "is_correct": null,
        "time_taken": 0,
        "marks_earned": 0,
        "marks_deducted": 0
    },
    {
        "quiz_session_id": 5,
        "sno": 1,
        "question_id": 1,
        "original_question": "<p>What is the charge of an electron?</p>",
        "options": "a:2:{i:0;s:15:\"<p>Positive</p>\";i:1;s:15:\"<p>Negative</p>\";}",
        "user_answer": "N;",
        "correct_answer": "i:2;",
        "status": "not_answered",
        "is_correct": 0,
        "time_taken": 2,
        "marks_earned": 0,
        "marks_deducted": 0
    },
    {
        "quiz_session_id": 5,
        "sno": 2,
        "question_id": 2,
        "original_question": "<p>What is the order of fundamental forces in nature according to their strengths.</p>",
        "options": "a:2:{s:7:\"matches\";a:4:{i:0;a:2:{s:2:\"id\";s:32:\"c215fc75951b35c5847a807240fab2ea\";s:5:\"value\";s:20:\"<p>Nuclear Force</p>\";}i:1;a:2:{s:2:\"id\";s:32:\"a9577d25b70d4788551133ae4f265347\";s:5:\"value\";s:27:\"<p>Electomagnetic Force</p>\";}i:2;a:2:{s:2:\"id\";s:32:\"2577539023dcd204eb78a3ad1cd6201c\";s:5:\"value\";s:25:\"<p>Weak Nuclear Force</p>\";}i:3;a:2:{s:2:\"id\";s:32:\"19be0e556de5c94f431c8d9ced56641f\";s:5:\"value\";s:26:\"<p>Gravitational Force</p>\";}}s:5:\"pairs\";a:4:{i:0;a:3:{s:2:\"id\";s:32:\"1d996b61ee20735a967752c065fd62b0\";s:5:\"value\";s:8:\"<p>3</p>\";s:4:\"code\";s:1:\"A\";}i:1;a:3:{s:2:\"id\";s:32:\"d1a89b1335613b7b84b5426e0ef6452a\";s:5:\"value\";s:8:\"<p>2</p>\";s:4:\"code\";s:1:\"B\";}i:2;a:3:{s:2:\"id\";s:32:\"a22d6a95d33b5208f04eedb325282800\";s:5:\"value\";s:8:\"<p>1</p>\";s:4:\"code\";s:1:\"C\";}i:3;a:3:{s:2:\"id\";s:32:\"7667e2cd947e57f259549e120bbc619d\";s:5:\"value\";s:8:\"<p>4</p>\";s:4:\"code\";s:1:\"D\";}}}",
        "user_answer": null,
        "correct_answer": "a:4:{i:0;s:32:\"a22d6a95d33b5208f04eedb325282800\";i:1;s:32:\"d1a89b1335613b7b84b5426e0ef6452a\";i:2;s:32:\"1d996b61ee20735a967752c065fd62b0\";i:3;s:32:\"7667e2cd947e57f259549e120bbc619d\";}",
        "status": "not_visited",
        "is_correct": null,
        "time_taken": 0,
        "marks_earned": 0,
        "marks_deducted": 0
    },
    {
        "quiz_session_id": 6,
        "sno": 1,
        "question_id": 1,
        "original_question": "<p>What is the charge of an electron?</p>",
        "options": "a:2:{i:0;s:15:\"<p>Positive</p>\";i:1;s:15:\"<p>Negative</p>\";}",
        "user_answer": null,
        "correct_answer": "i:2;",
        "status": "not_visited",
        "is_correct": null,
        "time_taken": 0,
        "marks_earned": 0,
        "marks_deducted": 0
    },
    {
        "quiz_session_id": 6,
        "sno": 2,
        "question_id": 2,
        "original_question": "<p>What is the order of fundamental forces in nature according to their strengths.</p>",
        "options": "a:2:{s:7:\"matches\";a:4:{i:0;a:2:{s:2:\"id\";s:32:\"c215fc75951b35c5847a807240fab2ea\";s:5:\"value\";s:20:\"<p>Nuclear Force</p>\";}i:1;a:2:{s:2:\"id\";s:32:\"a9577d25b70d4788551133ae4f265347\";s:5:\"value\";s:27:\"<p>Electomagnetic Force</p>\";}i:2;a:2:{s:2:\"id\";s:32:\"2577539023dcd204eb78a3ad1cd6201c\";s:5:\"value\";s:25:\"<p>Weak Nuclear Force</p>\";}i:3;a:2:{s:2:\"id\";s:32:\"19be0e556de5c94f431c8d9ced56641f\";s:5:\"value\";s:26:\"<p>Gravitational Force</p>\";}}s:5:\"pairs\";a:4:{i:0;a:3:{s:2:\"id\";s:32:\"7667e2cd947e57f259549e120bbc619d\";s:5:\"value\";s:8:\"<p>4</p>\";s:4:\"code\";s:1:\"A\";}i:1;a:3:{s:2:\"id\";s:32:\"a22d6a95d33b5208f04eedb325282800\";s:5:\"value\";s:8:\"<p>1</p>\";s:4:\"code\";s:1:\"B\";}i:2;a:3:{s:2:\"id\";s:32:\"d1a89b1335613b7b84b5426e0ef6452a\";s:5:\"value\";s:8:\"<p>2</p>\";s:4:\"code\";s:1:\"C\";}i:3;a:3:{s:2:\"id\";s:32:\"1d996b61ee20735a967752c065fd62b0\";s:5:\"value\";s:8:\"<p>3</p>\";s:4:\"code\";s:1:\"D\";}}}",
        "user_answer": null,
        "correct_answer": "a:4:{i:0;s:32:\"a22d6a95d33b5208f04eedb325282800\";i:1;s:32:\"d1a89b1335613b7b84b5426e0ef6452a\";i:2;s:32:\"1d996b61ee20735a967752c065fd62b0\";i:3;s:32:\"7667e2cd947e57f259549e120bbc619d\";}",
        "status": "not_visited",
        "is_correct": null,
        "time_taken": 0,
        "marks_earned": 0,
        "marks_deducted": 0
    },
    {
        "quiz_session_id": 7,
        "sno": 2,
        "question_id": 1,
        "original_question": "<p>What is the charge of an electron?</p>",
        "options": "a:2:{i:0;s:15:\"<p>Positive</p>\";i:1;s:15:\"<p>Negative</p>\";}",
        "user_answer": null,
        "correct_answer": "i:2;",
        "status": "not_visited",
        "is_correct": null,
        "time_taken": 0,
        "marks_earned": 0,
        "marks_deducted": 0
    },
    {
        "quiz_session_id": 7,
        "sno": 1,
        "question_id": 2,
        "original_question": "<p>What is the order of fundamental forces in nature according to their strengths.</p>",
        "options": "a:2:{s:7:\"matches\";a:4:{i:0;a:2:{s:2:\"id\";s:32:\"c215fc75951b35c5847a807240fab2ea\";s:5:\"value\";s:20:\"<p>Nuclear Force</p>\";}i:1;a:2:{s:2:\"id\";s:32:\"a9577d25b70d4788551133ae4f265347\";s:5:\"value\";s:27:\"<p>Electomagnetic Force</p>\";}i:2;a:2:{s:2:\"id\";s:32:\"2577539023dcd204eb78a3ad1cd6201c\";s:5:\"value\";s:25:\"<p>Weak Nuclear Force</p>\";}i:3;a:2:{s:2:\"id\";s:32:\"19be0e556de5c94f431c8d9ced56641f\";s:5:\"value\";s:26:\"<p>Gravitational Force</p>\";}}s:5:\"pairs\";a:4:{i:0;a:3:{s:2:\"id\";s:32:\"d1a89b1335613b7b84b5426e0ef6452a\";s:5:\"value\";s:8:\"<p>2</p>\";s:4:\"code\";s:1:\"A\";}i:1;a:3:{s:2:\"id\";s:32:\"7667e2cd947e57f259549e120bbc619d\";s:5:\"value\";s:8:\"<p>4</p>\";s:4:\"code\";s:1:\"B\";}i:2;a:3:{s:2:\"id\";s:32:\"a22d6a95d33b5208f04eedb325282800\";s:5:\"value\";s:8:\"<p>1</p>\";s:4:\"code\";s:1:\"C\";}i:3;a:3:{s:2:\"id\";s:32:\"1d996b61ee20735a967752c065fd62b0\";s:5:\"value\";s:8:\"<p>3</p>\";s:4:\"code\";s:1:\"D\";}}}",
        "user_answer": null,
        "correct_answer": "a:4:{i:0;s:32:\"a22d6a95d33b5208f04eedb325282800\";i:1;s:32:\"d1a89b1335613b7b84b5426e0ef6452a\";i:2;s:32:\"1d996b61ee20735a967752c065fd62b0\";i:3;s:32:\"7667e2cd947e57f259549e120bbc619d\";}",
        "status": "not_visited",
        "is_correct": null,
        "time_taken": 0,
        "marks_earned": 0,
        "marks_deducted": 0
    },
    {
        "quiz_session_id": 8,
        "sno": 1,
        "question_id": 1,
        "original_question": "<p>What is the charge of an electron?</p>",
        "options": "a:2:{i:0;s:15:\"<p>Positive</p>\";i:1;s:15:\"<p>Negative</p>\";}",
        "user_answer": null,
        "correct_answer": "i:2;",
        "status": "not_visited",
        "is_correct": null,
        "time_taken": 0,
        "marks_earned": 0,
        "marks_deducted": 0
    },
    {
        "quiz_session_id": 8,
        "sno": 2,
        "question_id": 2,
        "original_question": "<p>What is the order of fundamental forces in nature according to their strengths.</p>",
        "options": "a:2:{s:7:\"matches\";a:4:{i:0;a:2:{s:2:\"id\";s:32:\"c215fc75951b35c5847a807240fab2ea\";s:5:\"value\";s:20:\"<p>Nuclear Force</p>\";}i:1;a:2:{s:2:\"id\";s:32:\"a9577d25b70d4788551133ae4f265347\";s:5:\"value\";s:27:\"<p>Electomagnetic Force</p>\";}i:2;a:2:{s:2:\"id\";s:32:\"2577539023dcd204eb78a3ad1cd6201c\";s:5:\"value\";s:25:\"<p>Weak Nuclear Force</p>\";}i:3;a:2:{s:2:\"id\";s:32:\"19be0e556de5c94f431c8d9ced56641f\";s:5:\"value\";s:26:\"<p>Gravitational Force</p>\";}}s:5:\"pairs\";a:4:{i:0;a:3:{s:2:\"id\";s:32:\"7667e2cd947e57f259549e120bbc619d\";s:5:\"value\";s:8:\"<p>4</p>\";s:4:\"code\";s:1:\"A\";}i:1;a:3:{s:2:\"id\";s:32:\"1d996b61ee20735a967752c065fd62b0\";s:5:\"value\";s:8:\"<p>3</p>\";s:4:\"code\";s:1:\"B\";}i:2;a:3:{s:2:\"id\";s:32:\"a22d6a95d33b5208f04eedb325282800\";s:5:\"value\";s:8:\"<p>1</p>\";s:4:\"code\";s:1:\"C\";}i:3;a:3:{s:2:\"id\";s:32:\"d1a89b1335613b7b84b5426e0ef6452a\";s:5:\"value\";s:8:\"<p>2</p>\";s:4:\"code\";s:1:\"D\";}}}",
        "user_answer": null,
        "correct_answer": "a:4:{i:0;s:32:\"a22d6a95d33b5208f04eedb325282800\";i:1;s:32:\"d1a89b1335613b7b84b5426e0ef6452a\";i:2;s:32:\"1d996b61ee20735a967752c065fd62b0\";i:3;s:32:\"7667e2cd947e57f259549e120bbc619d\";}",
        "status": "not_visited",
        "is_correct": null,
        "time_taken": 0,
        "marks_earned": 0,
        "marks_deducted": 0
    },
    {
        "quiz_session_id": 9,
        "sno": 1,
        "question_id": 1,
        "original_question": "<p>What is the charge of an electron?</p>",
        "options": "a:2:{i:0;s:15:\"<p>Positive</p>\";i:1;s:15:\"<p>Negative</p>\";}",
        "user_answer": "N;",
        "correct_answer": "i:2;",
        "status": "not_answered",
        "is_correct": 0,
        "time_taken": 6,
        "marks_earned": 0,
        "marks_deducted": 0
    },
    {
        "quiz_session_id": 9,
        "sno": 2,
        "question_id": 2,
        "original_question": "<p>What is the order of fundamental forces in nature according to their strengths.</p>",
        "options": "a:2:{s:7:\"matches\";a:4:{i:0;a:2:{s:2:\"id\";s:32:\"c215fc75951b35c5847a807240fab2ea\";s:5:\"value\";s:20:\"<p>Nuclear Force</p>\";}i:1;a:2:{s:2:\"id\";s:32:\"a9577d25b70d4788551133ae4f265347\";s:5:\"value\";s:27:\"<p>Electomagnetic Force</p>\";}i:2;a:2:{s:2:\"id\";s:32:\"2577539023dcd204eb78a3ad1cd6201c\";s:5:\"value\";s:25:\"<p>Weak Nuclear Force</p>\";}i:3;a:2:{s:2:\"id\";s:32:\"19be0e556de5c94f431c8d9ced56641f\";s:5:\"value\";s:26:\"<p>Gravitational Force</p>\";}}s:5:\"pairs\";a:4:{i:0;a:3:{s:2:\"id\";s:32:\"1d996b61ee20735a967752c065fd62b0\";s:5:\"value\";s:8:\"<p>3</p>\";s:4:\"code\";s:1:\"A\";}i:1;a:3:{s:2:\"id\";s:32:\"a22d6a95d33b5208f04eedb325282800\";s:5:\"value\";s:8:\"<p>1</p>\";s:4:\"code\";s:1:\"B\";}i:2;a:3:{s:2:\"id\";s:32:\"7667e2cd947e57f259549e120bbc619d\";s:5:\"value\";s:8:\"<p>4</p>\";s:4:\"code\";s:1:\"C\";}i:3;a:3:{s:2:\"id\";s:32:\"d1a89b1335613b7b84b5426e0ef6452a\";s:5:\"value\";s:8:\"<p>2</p>\";s:4:\"code\";s:1:\"D\";}}}",
        "user_answer": "a:0:{}",
        "correct_answer": "a:4:{i:0;s:32:\"a22d6a95d33b5208f04eedb325282800\";i:1;s:32:\"d1a89b1335613b7b84b5426e0ef6452a\";i:2;s:32:\"1d996b61ee20735a967752c065fd62b0\";i:3;s:32:\"7667e2cd947e57f259549e120bbc619d\";}",
        "status": "not_answered",
        "is_correct": 0,
        "time_taken": 8,
        "marks_earned": 0,
        "marks_deducted": 0
    },
    {
        "quiz_session_id": 10,
        "sno": 2,
        "question_id": 1,
        "original_question": "<p>What is the charge of an electron?</p>",
        "options": "a:2:{i:0;s:15:\"<p>Positive</p>\";i:1;s:15:\"<p>Negative</p>\";}",
        "user_answer": null,
        "correct_answer": "i:2;",
        "status": "not_visited",
        "is_correct": null,
        "time_taken": 0,
        "marks_earned": 0,
        "marks_deducted": 0
    },
    {
        "quiz_session_id": 10,
        "sno": 1,
        "question_id": 2,
        "original_question": "<p>What is the order of fundamental forces in nature according to their strengths.</p>",
        "options": "a:2:{s:7:\"matches\";a:4:{i:0;a:2:{s:2:\"id\";s:32:\"c215fc75951b35c5847a807240fab2ea\";s:5:\"value\";s:20:\"<p>Nuclear Force</p>\";}i:1;a:2:{s:2:\"id\";s:32:\"a9577d25b70d4788551133ae4f265347\";s:5:\"value\";s:27:\"<p>Electomagnetic Force</p>\";}i:2;a:2:{s:2:\"id\";s:32:\"2577539023dcd204eb78a3ad1cd6201c\";s:5:\"value\";s:25:\"<p>Weak Nuclear Force</p>\";}i:3;a:2:{s:2:\"id\";s:32:\"19be0e556de5c94f431c8d9ced56641f\";s:5:\"value\";s:26:\"<p>Gravitational Force</p>\";}}s:5:\"pairs\";a:4:{i:0;a:3:{s:2:\"id\";s:32:\"d1a89b1335613b7b84b5426e0ef6452a\";s:5:\"value\";s:8:\"<p>2</p>\";s:4:\"code\";s:1:\"A\";}i:1;a:3:{s:2:\"id\";s:32:\"7667e2cd947e57f259549e120bbc619d\";s:5:\"value\";s:8:\"<p>4</p>\";s:4:\"code\";s:1:\"B\";}i:2;a:3:{s:2:\"id\";s:32:\"a22d6a95d33b5208f04eedb325282800\";s:5:\"value\";s:8:\"<p>1</p>\";s:4:\"code\";s:1:\"C\";}i:3;a:3:{s:2:\"id\";s:32:\"1d996b61ee20735a967752c065fd62b0\";s:5:\"value\";s:8:\"<p>3</p>\";s:4:\"code\";s:1:\"D\";}}}",
        "user_answer": null,
        "correct_answer": "a:4:{i:0;s:32:\"a22d6a95d33b5208f04eedb325282800\";i:1;s:32:\"d1a89b1335613b7b84b5426e0ef6452a\";i:2;s:32:\"1d996b61ee20735a967752c065fd62b0\";i:3;s:32:\"7667e2cd947e57f259549e120bbc619d\";}",
        "status": "not_visited",
        "is_correct": null,
        "time_taken": 0,
        "marks_earned": 0,
        "marks_deducted": 0
    },
    {
        "quiz_session_id": 11,
        "sno": 2,
        "question_id": 1,
        "original_question": "<p>What is the charge of an electron?</p>",
        "options": "a:2:{i:0;s:15:\"<p>Positive</p>\";i:1;s:15:\"<p>Negative</p>\";}",
        "user_answer": null,
        "correct_answer": "i:2;",
        "status": "not_visited",
        "is_correct": null,
        "time_taken": 0,
        "marks_earned": 0,
        "marks_deducted": 0
    },
    {
        "quiz_session_id": 11,
        "sno": 1,
        "question_id": 2,
        "original_question": "<p>What is the order of fundamental forces in nature according to their strengths.</p>",
        "options": "a:2:{s:7:\"matches\";a:4:{i:0;a:2:{s:2:\"id\";s:32:\"c215fc75951b35c5847a807240fab2ea\";s:5:\"value\";s:20:\"<p>Nuclear Force</p>\";}i:1;a:2:{s:2:\"id\";s:32:\"a9577d25b70d4788551133ae4f265347\";s:5:\"value\";s:27:\"<p>Electomagnetic Force</p>\";}i:2;a:2:{s:2:\"id\";s:32:\"2577539023dcd204eb78a3ad1cd6201c\";s:5:\"value\";s:25:\"<p>Weak Nuclear Force</p>\";}i:3;a:2:{s:2:\"id\";s:32:\"19be0e556de5c94f431c8d9ced56641f\";s:5:\"value\";s:26:\"<p>Gravitational Force</p>\";}}s:5:\"pairs\";a:4:{i:0;a:3:{s:2:\"id\";s:32:\"7667e2cd947e57f259549e120bbc619d\";s:5:\"value\";s:8:\"<p>4</p>\";s:4:\"code\";s:1:\"A\";}i:1;a:3:{s:2:\"id\";s:32:\"d1a89b1335613b7b84b5426e0ef6452a\";s:5:\"value\";s:8:\"<p>2</p>\";s:4:\"code\";s:1:\"B\";}i:2;a:3:{s:2:\"id\";s:32:\"1d996b61ee20735a967752c065fd62b0\";s:5:\"value\";s:8:\"<p>3</p>\";s:4:\"code\";s:1:\"C\";}i:3;a:3:{s:2:\"id\";s:32:\"a22d6a95d33b5208f04eedb325282800\";s:5:\"value\";s:8:\"<p>1</p>\";s:4:\"code\";s:1:\"D\";}}}",
        "user_answer": null,
        "correct_answer": "a:4:{i:0;s:32:\"a22d6a95d33b5208f04eedb325282800\";i:1;s:32:\"d1a89b1335613b7b84b5426e0ef6452a\";i:2;s:32:\"1d996b61ee20735a967752c065fd62b0\";i:3;s:32:\"7667e2cd947e57f259549e120bbc619d\";}",
        "status": "not_visited",
        "is_correct": null,
        "time_taken": 0,
        "marks_earned": 0,
        "marks_deducted": 0
    },
    {
        "quiz_session_id": 12,
        "sno": 2,
        "question_id": 1,
        "original_question": "<p>What is the charge of an electron?</p>",
        "options": "a:2:{i:0;s:15:\"<p>Positive</p>\";i:1;s:15:\"<p>Negative</p>\";}",
        "user_answer": null,
        "correct_answer": "i:2;",
        "status": "not_visited",
        "is_correct": null,
        "time_taken": 0,
        "marks_earned": 0,
        "marks_deducted": 0
    },
    {
        "quiz_session_id": 12,
        "sno": 1,
        "question_id": 2,
        "original_question": "<p>What is the order of fundamental forces in nature according to their strengths.</p>",
        "options": "a:2:{s:7:\"matches\";a:4:{i:0;a:2:{s:2:\"id\";s:32:\"c215fc75951b35c5847a807240fab2ea\";s:5:\"value\";s:20:\"<p>Nuclear Force</p>\";}i:1;a:2:{s:2:\"id\";s:32:\"a9577d25b70d4788551133ae4f265347\";s:5:\"value\";s:27:\"<p>Electomagnetic Force</p>\";}i:2;a:2:{s:2:\"id\";s:32:\"2577539023dcd204eb78a3ad1cd6201c\";s:5:\"value\";s:25:\"<p>Weak Nuclear Force</p>\";}i:3;a:2:{s:2:\"id\";s:32:\"19be0e556de5c94f431c8d9ced56641f\";s:5:\"value\";s:26:\"<p>Gravitational Force</p>\";}}s:5:\"pairs\";a:4:{i:0;a:3:{s:2:\"id\";s:32:\"7667e2cd947e57f259549e120bbc619d\";s:5:\"value\";s:8:\"<p>4</p>\";s:4:\"code\";s:1:\"A\";}i:1;a:3:{s:2:\"id\";s:32:\"a22d6a95d33b5208f04eedb325282800\";s:5:\"value\";s:8:\"<p>1</p>\";s:4:\"code\";s:1:\"B\";}i:2;a:3:{s:2:\"id\";s:32:\"1d996b61ee20735a967752c065fd62b0\";s:5:\"value\";s:8:\"<p>3</p>\";s:4:\"code\";s:1:\"C\";}i:3;a:3:{s:2:\"id\";s:32:\"d1a89b1335613b7b84b5426e0ef6452a\";s:5:\"value\";s:8:\"<p>2</p>\";s:4:\"code\";s:1:\"D\";}}}",
        "user_answer": null,
        "correct_answer": "a:4:{i:0;s:32:\"a22d6a95d33b5208f04eedb325282800\";i:1;s:32:\"d1a89b1335613b7b84b5426e0ef6452a\";i:2;s:32:\"1d996b61ee20735a967752c065fd62b0\";i:3;s:32:\"7667e2cd947e57f259549e120bbc619d\";}",
        "status": "not_visited",
        "is_correct": null,
        "time_taken": 0,
        "marks_earned": 0,
        "marks_deducted": 0
    },
    {
        "quiz_session_id": 13,
        "sno": 1,
        "question_id": 1,
        "original_question": "<p>What is the charge of an electron?</p>",
        "options": "a:2:{i:0;s:15:\"<p>Positive</p>\";i:1;s:15:\"<p>Negative</p>\";}",
        "user_answer": null,
        "correct_answer": "i:2;",
        "status": "not_visited",
        "is_correct": null,
        "time_taken": 0,
        "marks_earned": 0,
        "marks_deducted": 0
    },
    {
        "quiz_session_id": 13,
        "sno": 2,
        "question_id": 2,
        "original_question": "<p>What is the order of fundamental forces in nature according to their strengths.</p>",
        "options": "a:2:{s:7:\"matches\";a:4:{i:0;a:2:{s:2:\"id\";s:32:\"c215fc75951b35c5847a807240fab2ea\";s:5:\"value\";s:20:\"<p>Nuclear Force</p>\";}i:1;a:2:{s:2:\"id\";s:32:\"a9577d25b70d4788551133ae4f265347\";s:5:\"value\";s:27:\"<p>Electomagnetic Force</p>\";}i:2;a:2:{s:2:\"id\";s:32:\"2577539023dcd204eb78a3ad1cd6201c\";s:5:\"value\";s:25:\"<p>Weak Nuclear Force</p>\";}i:3;a:2:{s:2:\"id\";s:32:\"19be0e556de5c94f431c8d9ced56641f\";s:5:\"value\";s:26:\"<p>Gravitational Force</p>\";}}s:5:\"pairs\";a:4:{i:0;a:3:{s:2:\"id\";s:32:\"a22d6a95d33b5208f04eedb325282800\";s:5:\"value\";s:8:\"<p>1</p>\";s:4:\"code\";s:1:\"A\";}i:1;a:3:{s:2:\"id\";s:32:\"d1a89b1335613b7b84b5426e0ef6452a\";s:5:\"value\";s:8:\"<p>2</p>\";s:4:\"code\";s:1:\"B\";}i:2;a:3:{s:2:\"id\";s:32:\"1d996b61ee20735a967752c065fd62b0\";s:5:\"value\";s:8:\"<p>3</p>\";s:4:\"code\";s:1:\"C\";}i:3;a:3:{s:2:\"id\";s:32:\"7667e2cd947e57f259549e120bbc619d\";s:5:\"value\";s:8:\"<p>4</p>\";s:4:\"code\";s:1:\"D\";}}}",
        "user_answer": null,
        "correct_answer": "a:4:{i:0;s:32:\"a22d6a95d33b5208f04eedb325282800\";i:1;s:32:\"d1a89b1335613b7b84b5426e0ef6452a\";i:2;s:32:\"1d996b61ee20735a967752c065fd62b0\";i:3;s:32:\"7667e2cd947e57f259549e120bbc619d\";}",
        "status": "not_visited",
        "is_correct": null,
        "time_taken": 0,
        "marks_earned": 0,
        "marks_deducted": 0
    },
    {
        "quiz_session_id": 14,
        "sno": 2,
        "question_id": 1,
        "original_question": "<p>What is the charge of an electron?</p>",
        "options": "a:2:{i:0;s:15:\"<p>Positive</p>\";i:1;s:15:\"<p>Negative</p>\";}",
        "user_answer": null,
        "correct_answer": "i:2;",
        "status": "not_visited",
        "is_correct": null,
        "time_taken": 0,
        "marks_earned": 0,
        "marks_deducted": 0
    },
    {
        "quiz_session_id": 14,
        "sno": 1,
        "question_id": 2,
        "original_question": "<p>What is the order of fundamental forces in nature according to their strengths.</p>",
        "options": "a:2:{s:7:\"matches\";a:4:{i:0;a:2:{s:2:\"id\";s:32:\"c215fc75951b35c5847a807240fab2ea\";s:5:\"value\";s:20:\"<p>Nuclear Force</p>\";}i:1;a:2:{s:2:\"id\";s:32:\"a9577d25b70d4788551133ae4f265347\";s:5:\"value\";s:27:\"<p>Electomagnetic Force</p>\";}i:2;a:2:{s:2:\"id\";s:32:\"2577539023dcd204eb78a3ad1cd6201c\";s:5:\"value\";s:25:\"<p>Weak Nuclear Force</p>\";}i:3;a:2:{s:2:\"id\";s:32:\"19be0e556de5c94f431c8d9ced56641f\";s:5:\"value\";s:26:\"<p>Gravitational Force</p>\";}}s:5:\"pairs\";a:4:{i:0;a:3:{s:2:\"id\";s:32:\"a22d6a95d33b5208f04eedb325282800\";s:5:\"value\";s:8:\"<p>1</p>\";s:4:\"code\";s:1:\"A\";}i:1;a:3:{s:2:\"id\";s:32:\"d1a89b1335613b7b84b5426e0ef6452a\";s:5:\"value\";s:8:\"<p>2</p>\";s:4:\"code\";s:1:\"B\";}i:2;a:3:{s:2:\"id\";s:32:\"1d996b61ee20735a967752c065fd62b0\";s:5:\"value\";s:8:\"<p>3</p>\";s:4:\"code\";s:1:\"C\";}i:3;a:3:{s:2:\"id\";s:32:\"7667e2cd947e57f259549e120bbc619d\";s:5:\"value\";s:8:\"<p>4</p>\";s:4:\"code\";s:1:\"D\";}}}",
        "user_answer": "a:0:{}",
        "correct_answer": "a:4:{i:0;s:32:\"a22d6a95d33b5208f04eedb325282800\";i:1;s:32:\"d1a89b1335613b7b84b5426e0ef6452a\";i:2;s:32:\"1d996b61ee20735a967752c065fd62b0\";i:3;s:32:\"7667e2cd947e57f259549e120bbc619d\";}",
        "status": "not_answered",
        "is_correct": 0,
        "time_taken": 228,
        "marks_earned": 0,
        "marks_deducted": 0
    },
    {
        "quiz_session_id": 15,
        "sno": 1,
        "question_id": 1,
        "original_question": "<p>What is the charge of an electron?</p>",
        "options": "a:2:{i:0;s:15:\"<p>Positive</p>\";i:1;s:15:\"<p>Negative</p>\";}",
        "user_answer": null,
        "correct_answer": "i:2;",
        "status": "not_visited",
        "is_correct": null,
        "time_taken": 0,
        "marks_earned": 0,
        "marks_deducted": 0
    },
    {
        "quiz_session_id": 15,
        "sno": 2,
        "question_id": 2,
        "original_question": "<p>What is the order of fundamental forces in nature according to their strengths.</p>",
        "options": "a:2:{s:7:\"matches\";a:4:{i:0;a:2:{s:2:\"id\";s:32:\"c215fc75951b35c5847a807240fab2ea\";s:5:\"value\";s:20:\"<p>Nuclear Force</p>\";}i:1;a:2:{s:2:\"id\";s:32:\"a9577d25b70d4788551133ae4f265347\";s:5:\"value\";s:27:\"<p>Electomagnetic Force</p>\";}i:2;a:2:{s:2:\"id\";s:32:\"2577539023dcd204eb78a3ad1cd6201c\";s:5:\"value\";s:25:\"<p>Weak Nuclear Force</p>\";}i:3;a:2:{s:2:\"id\";s:32:\"19be0e556de5c94f431c8d9ced56641f\";s:5:\"value\";s:26:\"<p>Gravitational Force</p>\";}}s:5:\"pairs\";a:4:{i:0;a:3:{s:2:\"id\";s:32:\"d1a89b1335613b7b84b5426e0ef6452a\";s:5:\"value\";s:8:\"<p>2</p>\";s:4:\"code\";s:1:\"A\";}i:1;a:3:{s:2:\"id\";s:32:\"a22d6a95d33b5208f04eedb325282800\";s:5:\"value\";s:8:\"<p>1</p>\";s:4:\"code\";s:1:\"B\";}i:2;a:3:{s:2:\"id\";s:32:\"7667e2cd947e57f259549e120bbc619d\";s:5:\"value\";s:8:\"<p>4</p>\";s:4:\"code\";s:1:\"C\";}i:3;a:3:{s:2:\"id\";s:32:\"1d996b61ee20735a967752c065fd62b0\";s:5:\"value\";s:8:\"<p>3</p>\";s:4:\"code\";s:1:\"D\";}}}",
        "user_answer": null,
        "correct_answer": "a:4:{i:0;s:32:\"a22d6a95d33b5208f04eedb325282800\";i:1;s:32:\"d1a89b1335613b7b84b5426e0ef6452a\";i:2;s:32:\"1d996b61ee20735a967752c065fd62b0\";i:3;s:32:\"7667e2cd947e57f259549e120bbc619d\";}",
        "status": "not_visited",
        "is_correct": null,
        "time_taken": 0,
        "marks_earned": 0,
        "marks_deducted": 0
    },
    {
        "quiz_session_id": 16,
        "sno": 2,
        "question_id": 1,
        "original_question": "<p>What is the charge of an electron?</p>",
        "options": "a:2:{i:0;s:15:\"<p>Positive</p>\";i:1;s:15:\"<p>Negative</p>\";}",
        "user_answer": null,
        "correct_answer": "i:2;",
        "status": "not_visited",
        "is_correct": null,
        "time_taken": 0,
        "marks_earned": 0,
        "marks_deducted": 0
    },
    {
        "quiz_session_id": 16,
        "sno": 1,
        "question_id": 2,
        "original_question": "<p>What is the order of fundamental forces in nature according to their strengths.</p>",
        "options": "a:2:{s:7:\"matches\";a:4:{i:0;a:2:{s:2:\"id\";s:32:\"c215fc75951b35c5847a807240fab2ea\";s:5:\"value\";s:20:\"<p>Nuclear Force</p>\";}i:1;a:2:{s:2:\"id\";s:32:\"a9577d25b70d4788551133ae4f265347\";s:5:\"value\";s:27:\"<p>Electomagnetic Force</p>\";}i:2;a:2:{s:2:\"id\";s:32:\"2577539023dcd204eb78a3ad1cd6201c\";s:5:\"value\";s:25:\"<p>Weak Nuclear Force</p>\";}i:3;a:2:{s:2:\"id\";s:32:\"19be0e556de5c94f431c8d9ced56641f\";s:5:\"value\";s:26:\"<p>Gravitational Force</p>\";}}s:5:\"pairs\";a:4:{i:0;a:3:{s:2:\"id\";s:32:\"7667e2cd947e57f259549e120bbc619d\";s:5:\"value\";s:8:\"<p>4</p>\";s:4:\"code\";s:1:\"A\";}i:1;a:3:{s:2:\"id\";s:32:\"1d996b61ee20735a967752c065fd62b0\";s:5:\"value\";s:8:\"<p>3</p>\";s:4:\"code\";s:1:\"B\";}i:2;a:3:{s:2:\"id\";s:32:\"a22d6a95d33b5208f04eedb325282800\";s:5:\"value\";s:8:\"<p>1</p>\";s:4:\"code\";s:1:\"C\";}i:3;a:3:{s:2:\"id\";s:32:\"d1a89b1335613b7b84b5426e0ef6452a\";s:5:\"value\";s:8:\"<p>2</p>\";s:4:\"code\";s:1:\"D\";}}}",
        "user_answer": null,
        "correct_answer": "a:4:{i:0;s:32:\"a22d6a95d33b5208f04eedb325282800\";i:1;s:32:\"d1a89b1335613b7b84b5426e0ef6452a\";i:2;s:32:\"1d996b61ee20735a967752c065fd62b0\";i:3;s:32:\"7667e2cd947e57f259549e120bbc619d\";}",
        "status": "not_visited",
        "is_correct": null,
        "time_taken": 0,
        "marks_earned": 0,
        "marks_deducted": 0
    },
    {
        "quiz_session_id": 17,
        "sno": 1,
        "question_id": 1,
        "original_question": "<p>What is the charge of an electron?</p>",
        "options": "a:2:{i:0;s:15:\"<p>Positive</p>\";i:1;s:15:\"<p>Negative</p>\";}",
        "user_answer": null,
        "correct_answer": "i:2;",
        "status": "not_visited",
        "is_correct": null,
        "time_taken": 0,
        "marks_earned": 0,
        "marks_deducted": 0
    },
    {
        "quiz_session_id": 17,
        "sno": 2,
        "question_id": 2,
        "original_question": "<p>What is the order of fundamental forces in nature according to their strengths.</p>",
        "options": "a:2:{s:7:\"matches\";a:4:{i:0;a:2:{s:2:\"id\";s:32:\"c215fc75951b35c5847a807240fab2ea\";s:5:\"value\";s:20:\"<p>Nuclear Force</p>\";}i:1;a:2:{s:2:\"id\";s:32:\"a9577d25b70d4788551133ae4f265347\";s:5:\"value\";s:27:\"<p>Electomagnetic Force</p>\";}i:2;a:2:{s:2:\"id\";s:32:\"2577539023dcd204eb78a3ad1cd6201c\";s:5:\"value\";s:25:\"<p>Weak Nuclear Force</p>\";}i:3;a:2:{s:2:\"id\";s:32:\"19be0e556de5c94f431c8d9ced56641f\";s:5:\"value\";s:26:\"<p>Gravitational Force</p>\";}}s:5:\"pairs\";a:4:{i:0;a:3:{s:2:\"id\";s:32:\"7667e2cd947e57f259549e120bbc619d\";s:5:\"value\";s:8:\"<p>4</p>\";s:4:\"code\";s:1:\"A\";}i:1;a:3:{s:2:\"id\";s:32:\"1d996b61ee20735a967752c065fd62b0\";s:5:\"value\";s:8:\"<p>3</p>\";s:4:\"code\";s:1:\"B\";}i:2;a:3:{s:2:\"id\";s:32:\"a22d6a95d33b5208f04eedb325282800\";s:5:\"value\";s:8:\"<p>1</p>\";s:4:\"code\";s:1:\"C\";}i:3;a:3:{s:2:\"id\";s:32:\"d1a89b1335613b7b84b5426e0ef6452a\";s:5:\"value\";s:8:\"<p>2</p>\";s:4:\"code\";s:1:\"D\";}}}",
        "user_answer": "a:0:{}",
        "correct_answer": "a:4:{i:0;s:32:\"a22d6a95d33b5208f04eedb325282800\";i:1;s:32:\"d1a89b1335613b7b84b5426e0ef6452a\";i:2;s:32:\"1d996b61ee20735a967752c065fd62b0\";i:3;s:32:\"7667e2cd947e57f259549e120bbc619d\";}",
        "status": "not_answered",
        "is_correct": 0,
        "time_taken": 151,
        "marks_earned": 0,
        "marks_deducted": 0
    },
    {
        "quiz_session_id": 18,
        "sno": 1,
        "question_id": 1,
        "original_question": "<p>What is the charge of an electron?</p>",
        "options": "a:2:{i:0;s:15:\"<p>Positive</p>\";i:1;s:15:\"<p>Negative</p>\";}",
        "user_answer": null,
        "correct_answer": "i:2;",
        "status": "not_visited",
        "is_correct": null,
        "time_taken": 0,
        "marks_earned": 0,
        "marks_deducted": 0
    },
    {
        "quiz_session_id": 18,
        "sno": 2,
        "question_id": 2,
        "original_question": "<p>What is the order of fundamental forces in nature according to their strengths.</p>",
        "options": "a:2:{s:7:\"matches\";a:4:{i:0;a:2:{s:2:\"id\";s:32:\"c215fc75951b35c5847a807240fab2ea\";s:5:\"value\";s:20:\"<p>Nuclear Force</p>\";}i:1;a:2:{s:2:\"id\";s:32:\"a9577d25b70d4788551133ae4f265347\";s:5:\"value\";s:27:\"<p>Electomagnetic Force</p>\";}i:2;a:2:{s:2:\"id\";s:32:\"2577539023dcd204eb78a3ad1cd6201c\";s:5:\"value\";s:25:\"<p>Weak Nuclear Force</p>\";}i:3;a:2:{s:2:\"id\";s:32:\"19be0e556de5c94f431c8d9ced56641f\";s:5:\"value\";s:26:\"<p>Gravitational Force</p>\";}}s:5:\"pairs\";a:4:{i:0;a:3:{s:2:\"id\";s:32:\"1d996b61ee20735a967752c065fd62b0\";s:5:\"value\";s:8:\"<p>3</p>\";s:4:\"code\";s:1:\"A\";}i:1;a:3:{s:2:\"id\";s:32:\"a22d6a95d33b5208f04eedb325282800\";s:5:\"value\";s:8:\"<p>1</p>\";s:4:\"code\";s:1:\"B\";}i:2;a:3:{s:2:\"id\";s:32:\"d1a89b1335613b7b84b5426e0ef6452a\";s:5:\"value\";s:8:\"<p>2</p>\";s:4:\"code\";s:1:\"C\";}i:3;a:3:{s:2:\"id\";s:32:\"7667e2cd947e57f259549e120bbc619d\";s:5:\"value\";s:8:\"<p>4</p>\";s:4:\"code\";s:1:\"D\";}}}",
        "user_answer": "a:0:{}",
        "correct_answer": "a:4:{i:0;s:32:\"a22d6a95d33b5208f04eedb325282800\";i:1;s:32:\"d1a89b1335613b7b84b5426e0ef6452a\";i:2;s:32:\"1d996b61ee20735a967752c065fd62b0\";i:3;s:32:\"7667e2cd947e57f259549e120bbc619d\";}",
        "status": "not_answered",
        "is_correct": 0,
        "time_taken": 347,
        "marks_earned": 0,
        "marks_deducted": 0
    },
    {
        "quiz_session_id": 19,
        "sno": 2,
        "question_id": 1,
        "original_question": "<p>What is the charge of an electron?</p>",
        "options": "a:2:{i:0;s:15:\"<p>Positive</p>\";i:1;s:15:\"<p>Negative</p>\";}",
        "user_answer": "N;",
        "correct_answer": "i:2;",
        "status": "not_answered",
        "is_correct": 0,
        "time_taken": 78,
        "marks_earned": 0,
        "marks_deducted": 0
    },
    {
        "quiz_session_id": 19,
        "sno": 1,
        "question_id": 2,
        "original_question": "<p>What is the order of fundamental forces in nature according to their strengths.</p>",
        "options": "a:2:{s:7:\"matches\";a:4:{i:0;a:2:{s:2:\"id\";s:32:\"c215fc75951b35c5847a807240fab2ea\";s:5:\"value\";s:20:\"<p>Nuclear Force</p>\";}i:1;a:2:{s:2:\"id\";s:32:\"a9577d25b70d4788551133ae4f265347\";s:5:\"value\";s:27:\"<p>Electomagnetic Force</p>\";}i:2;a:2:{s:2:\"id\";s:32:\"2577539023dcd204eb78a3ad1cd6201c\";s:5:\"value\";s:25:\"<p>Weak Nuclear Force</p>\";}i:3;a:2:{s:2:\"id\";s:32:\"19be0e556de5c94f431c8d9ced56641f\";s:5:\"value\";s:26:\"<p>Gravitational Force</p>\";}}s:5:\"pairs\";a:4:{i:0;a:3:{s:2:\"id\";s:32:\"d1a89b1335613b7b84b5426e0ef6452a\";s:5:\"value\";s:8:\"<p>2</p>\";s:4:\"code\";s:1:\"A\";}i:1;a:3:{s:2:\"id\";s:32:\"1d996b61ee20735a967752c065fd62b0\";s:5:\"value\";s:8:\"<p>3</p>\";s:4:\"code\";s:1:\"B\";}i:2;a:3:{s:2:\"id\";s:32:\"a22d6a95d33b5208f04eedb325282800\";s:5:\"value\";s:8:\"<p>1</p>\";s:4:\"code\";s:1:\"C\";}i:3;a:3:{s:2:\"id\";s:32:\"7667e2cd947e57f259549e120bbc619d\";s:5:\"value\";s:8:\"<p>4</p>\";s:4:\"code\";s:1:\"D\";}}}",
        "user_answer": "a:0:{}",
        "correct_answer": "a:4:{i:0;s:32:\"a22d6a95d33b5208f04eedb325282800\";i:1;s:32:\"d1a89b1335613b7b84b5426e0ef6452a\";i:2;s:32:\"1d996b61ee20735a967752c065fd62b0\";i:3;s:32:\"7667e2cd947e57f259549e120bbc619d\";}",
        "status": "not_answered",
        "is_correct": 0,
        "time_taken": 31,
        "marks_earned": 0,
        "marks_deducted": 0
    },
    {
        "quiz_session_id": 20,
        "sno": 2,
        "question_id": 1,
        "original_question": "<p>What is the charge of an electron?</p>",
        "options": "a:2:{i:0;s:15:\"<p>Positive</p>\";i:1;s:15:\"<p>Negative</p>\";}",
        "user_answer": "i:1;",
        "correct_answer": "i:2;",
        "status": "answered",
        "is_correct": 0,
        "time_taken": 31,
        "marks_earned": 0,
        "marks_deducted": 0
    },
    {
        "quiz_session_id": 20,
        "sno": 1,
        "question_id": 2,
        "original_question": "<p>What is the order of fundamental forces in nature according to their strengths.</p>",
        "options": "a:2:{s:7:\"matches\";a:4:{i:0;a:2:{s:2:\"id\";s:32:\"c215fc75951b35c5847a807240fab2ea\";s:5:\"value\";s:20:\"<p>Nuclear Force</p>\";}i:1;a:2:{s:2:\"id\";s:32:\"a9577d25b70d4788551133ae4f265347\";s:5:\"value\";s:27:\"<p>Electomagnetic Force</p>\";}i:2;a:2:{s:2:\"id\";s:32:\"2577539023dcd204eb78a3ad1cd6201c\";s:5:\"value\";s:25:\"<p>Weak Nuclear Force</p>\";}i:3;a:2:{s:2:\"id\";s:32:\"19be0e556de5c94f431c8d9ced56641f\";s:5:\"value\";s:26:\"<p>Gravitational Force</p>\";}}s:5:\"pairs\";a:4:{i:0;a:3:{s:2:\"id\";s:32:\"7667e2cd947e57f259549e120bbc619d\";s:5:\"value\";s:8:\"<p>4</p>\";s:4:\"code\";s:1:\"A\";}i:1;a:3:{s:2:\"id\";s:32:\"1d996b61ee20735a967752c065fd62b0\";s:5:\"value\";s:8:\"<p>3</p>\";s:4:\"code\";s:1:\"B\";}i:2;a:3:{s:2:\"id\";s:32:\"a22d6a95d33b5208f04eedb325282800\";s:5:\"value\";s:8:\"<p>1</p>\";s:4:\"code\";s:1:\"C\";}i:3;a:3:{s:2:\"id\";s:32:\"d1a89b1335613b7b84b5426e0ef6452a\";s:5:\"value\";s:8:\"<p>2</p>\";s:4:\"code\";s:1:\"D\";}}}",
        "user_answer": null,
        "correct_answer": "a:4:{i:0;s:32:\"a22d6a95d33b5208f04eedb325282800\";i:1;s:32:\"d1a89b1335613b7b84b5426e0ef6452a\";i:2;s:32:\"1d996b61ee20735a967752c065fd62b0\";i:3;s:32:\"7667e2cd947e57f259549e120bbc619d\";}",
        "status": "not_visited",
        "is_correct": null,
        "time_taken": 0,
        "marks_earned": 0,
        "marks_deducted": 0
    },
    {
        "quiz_session_id": 21,
        "sno": 1,
        "question_id": 1,
        "original_question": "<p>What is the charge of an electron?</p>",
        "options": "a:2:{i:0;s:15:\"<p>Positive</p>\";i:1;s:15:\"<p>Negative</p>\";}",
        "user_answer": "i:2;",
        "correct_answer": "i:2;",
        "status": "answered",
        "is_correct": 1,
        "time_taken": 4,
        "marks_earned": 300,
        "marks_deducted": 0
    },
    {
        "quiz_session_id": 21,
        "sno": 2,
        "question_id": 2,
        "original_question": "<p>What is the order of fundamental forces in nature according to their strengths.</p>",
        "options": "a:2:{s:7:\"matches\";a:4:{i:0;a:2:{s:2:\"id\";s:32:\"c215fc75951b35c5847a807240fab2ea\";s:5:\"value\";s:20:\"<p>Nuclear Force</p>\";}i:1;a:2:{s:2:\"id\";s:32:\"a9577d25b70d4788551133ae4f265347\";s:5:\"value\";s:27:\"<p>Electomagnetic Force</p>\";}i:2;a:2:{s:2:\"id\";s:32:\"2577539023dcd204eb78a3ad1cd6201c\";s:5:\"value\";s:25:\"<p>Weak Nuclear Force</p>\";}i:3;a:2:{s:2:\"id\";s:32:\"19be0e556de5c94f431c8d9ced56641f\";s:5:\"value\";s:26:\"<p>Gravitational Force</p>\";}}s:5:\"pairs\";a:4:{i:0;a:3:{s:2:\"id\";s:32:\"a22d6a95d33b5208f04eedb325282800\";s:5:\"value\";s:8:\"<p>1</p>\";s:4:\"code\";s:1:\"A\";}i:1;a:3:{s:2:\"id\";s:32:\"7667e2cd947e57f259549e120bbc619d\";s:5:\"value\";s:8:\"<p>4</p>\";s:4:\"code\";s:1:\"B\";}i:2;a:3:{s:2:\"id\";s:32:\"d1a89b1335613b7b84b5426e0ef6452a\";s:5:\"value\";s:8:\"<p>2</p>\";s:4:\"code\";s:1:\"C\";}i:3;a:3:{s:2:\"id\";s:32:\"1d996b61ee20735a967752c065fd62b0\";s:5:\"value\";s:8:\"<p>3</p>\";s:4:\"code\";s:1:\"D\";}}}",
        "user_answer": "a:4:{i:0;a:3:{s:2:\"id\";s:32:\"a22d6a95d33b5208f04eedb325282800\";s:5:\"value\";s:8:\"<p>1</p>\";s:4:\"code\";s:1:\"A\";}i:1;a:3:{s:2:\"id\";s:32:\"d1a89b1335613b7b84b5426e0ef6452a\";s:5:\"value\";s:8:\"<p>2</p>\";s:4:\"code\";s:1:\"C\";}i:2;a:3:{s:2:\"id\";s:32:\"1d996b61ee20735a967752c065fd62b0\";s:5:\"value\";s:8:\"<p>3</p>\";s:4:\"code\";s:1:\"D\";}i:3;a:3:{s:2:\"id\";s:32:\"7667e2cd947e57f259549e120bbc619d\";s:5:\"value\";s:8:\"<p>4</p>\";s:4:\"code\";s:1:\"B\";}}",
        "correct_answer": "a:4:{i:0;s:32:\"a22d6a95d33b5208f04eedb325282800\";i:1;s:32:\"d1a89b1335613b7b84b5426e0ef6452a\";i:2;s:32:\"1d996b61ee20735a967752c065fd62b0\";i:3;s:32:\"7667e2cd947e57f259549e120bbc619d\";}",
        "status": "answered",
        "is_correct": 1,
        "time_taken": 84,
        "marks_earned": 300,
        "marks_deducted": 0
    },
    {
        "quiz_session_id": 22,
        "sno": 1,
        "question_id": 1,
        "original_question": "<p>What is the charge of an electron?</p>",
        "options": "a:2:{i:0;s:15:\"<p>Positive</p>\";i:1;s:15:\"<p>Negative</p>\";}",
        "user_answer": "N;",
        "correct_answer": "i:2;",
        "status": "not_answered",
        "is_correct": 0,
        "time_taken": 13,
        "marks_earned": 0,
        "marks_deducted": 0
    },
    {
        "quiz_session_id": 22,
        "sno": 2,
        "question_id": 2,
        "original_question": "<p>What is the order of fundamental forces in nature according to their strengths.</p>",
        "options": "a:2:{s:7:\"matches\";a:4:{i:0;a:2:{s:2:\"id\";s:32:\"c215fc75951b35c5847a807240fab2ea\";s:5:\"value\";s:20:\"<p>Nuclear Force</p>\";}i:1;a:2:{s:2:\"id\";s:32:\"a9577d25b70d4788551133ae4f265347\";s:5:\"value\";s:27:\"<p>Electomagnetic Force</p>\";}i:2;a:2:{s:2:\"id\";s:32:\"2577539023dcd204eb78a3ad1cd6201c\";s:5:\"value\";s:25:\"<p>Weak Nuclear Force</p>\";}i:3;a:2:{s:2:\"id\";s:32:\"19be0e556de5c94f431c8d9ced56641f\";s:5:\"value\";s:26:\"<p>Gravitational Force</p>\";}}s:5:\"pairs\";a:4:{i:0;a:3:{s:2:\"id\";s:32:\"a22d6a95d33b5208f04eedb325282800\";s:5:\"value\";s:8:\"<p>1</p>\";s:4:\"code\";s:1:\"A\";}i:1;a:3:{s:2:\"id\";s:32:\"d1a89b1335613b7b84b5426e0ef6452a\";s:5:\"value\";s:8:\"<p>2</p>\";s:4:\"code\";s:1:\"B\";}i:2;a:3:{s:2:\"id\";s:32:\"7667e2cd947e57f259549e120bbc619d\";s:5:\"value\";s:8:\"<p>4</p>\";s:4:\"code\";s:1:\"C\";}i:3;a:3:{s:2:\"id\";s:32:\"1d996b61ee20735a967752c065fd62b0\";s:5:\"value\";s:8:\"<p>3</p>\";s:4:\"code\";s:1:\"D\";}}}",
        "user_answer": null,
        "correct_answer": "a:4:{i:0;s:32:\"a22d6a95d33b5208f04eedb325282800\";i:1;s:32:\"d1a89b1335613b7b84b5426e0ef6452a\";i:2;s:32:\"1d996b61ee20735a967752c065fd62b0\";i:3;s:32:\"7667e2cd947e57f259549e120bbc619d\";}",
        "status": "not_visited",
        "is_correct": null,
        "time_taken": 0,
        "marks_earned": 0,
        "marks_deducted": 0
    },
    {
        "quiz_session_id": 23,
        "sno": 2,
        "question_id": 1,
        "original_question": "<p>What is the charge of an electron?</p>",
        "options": "a:2:{i:0;s:15:\"<p>Positive</p>\";i:1;s:15:\"<p>Negative</p>\";}",
        "user_answer": "N;",
        "correct_answer": "i:2;",
        "status": "not_answered",
        "is_correct": 0,
        "time_taken": 156,
        "marks_earned": 0,
        "marks_deducted": 0
    },
    {
        "quiz_session_id": 23,
        "sno": 1,
        "question_id": 2,
        "original_question": "<p>What is the order of fundamental forces in nature according to their strengths.</p>",
        "options": "a:2:{s:7:\"matches\";a:4:{i:0;a:2:{s:2:\"id\";s:32:\"c215fc75951b35c5847a807240fab2ea\";s:5:\"value\";s:20:\"<p>Nuclear Force</p>\";}i:1;a:2:{s:2:\"id\";s:32:\"a9577d25b70d4788551133ae4f265347\";s:5:\"value\";s:27:\"<p>Electomagnetic Force</p>\";}i:2;a:2:{s:2:\"id\";s:32:\"2577539023dcd204eb78a3ad1cd6201c\";s:5:\"value\";s:25:\"<p>Weak Nuclear Force</p>\";}i:3;a:2:{s:2:\"id\";s:32:\"19be0e556de5c94f431c8d9ced56641f\";s:5:\"value\";s:26:\"<p>Gravitational Force</p>\";}}s:5:\"pairs\";a:4:{i:0;a:3:{s:2:\"id\";s:32:\"7667e2cd947e57f259549e120bbc619d\";s:5:\"value\";s:8:\"<p>4</p>\";s:4:\"code\";s:1:\"A\";}i:1;a:3:{s:2:\"id\";s:32:\"d1a89b1335613b7b84b5426e0ef6452a\";s:5:\"value\";s:8:\"<p>2</p>\";s:4:\"code\";s:1:\"B\";}i:2;a:3:{s:2:\"id\";s:32:\"a22d6a95d33b5208f04eedb325282800\";s:5:\"value\";s:8:\"<p>1</p>\";s:4:\"code\";s:1:\"C\";}i:3;a:3:{s:2:\"id\";s:32:\"1d996b61ee20735a967752c065fd62b0\";s:5:\"value\";s:8:\"<p>3</p>\";s:4:\"code\";s:1:\"D\";}}}",
        "user_answer": null,
        "correct_answer": "a:4:{i:0;s:32:\"a22d6a95d33b5208f04eedb325282800\";i:1;s:32:\"d1a89b1335613b7b84b5426e0ef6452a\";i:2;s:32:\"1d996b61ee20735a967752c065fd62b0\";i:3;s:32:\"7667e2cd947e57f259549e120bbc619d\";}",
        "status": "not_visited",
        "is_correct": null,
        "time_taken": 0,
        "marks_earned": 0,
        "marks_deducted": 0
    },
    {
        "quiz_session_id": 24,
        "sno": 2,
        "question_id": 1,
        "original_question": "<p>What is the charge of an electron?</p>",
        "options": "a:2:{i:0;s:15:\"<p>Positive</p>\";i:1;s:15:\"<p>Negative</p>\";}",
        "user_answer": "i:2;",
        "correct_answer": "i:2;",
        "status": "answered",
        "is_correct": 1,
        "time_taken": 25,
        "marks_earned": 300,
        "marks_deducted": 0
    },
    {
        "quiz_session_id": 24,
        "sno": 3,
        "question_id": 2,
        "original_question": "<p>What is the order of fundamental forces in nature according to their strengths.</p>",
        "options": "a:2:{s:7:\"matches\";a:4:{i:0;a:2:{s:2:\"id\";s:32:\"c215fc75951b35c5847a807240fab2ea\";s:5:\"value\";s:20:\"<p>Nuclear Force</p>\";}i:1;a:2:{s:2:\"id\";s:32:\"a9577d25b70d4788551133ae4f265347\";s:5:\"value\";s:27:\"<p>Electomagnetic Force</p>\";}i:2;a:2:{s:2:\"id\";s:32:\"2577539023dcd204eb78a3ad1cd6201c\";s:5:\"value\";s:25:\"<p>Weak Nuclear Force</p>\";}i:3;a:2:{s:2:\"id\";s:32:\"19be0e556de5c94f431c8d9ced56641f\";s:5:\"value\";s:26:\"<p>Gravitational Force</p>\";}}s:5:\"pairs\";a:4:{i:0;a:3:{s:2:\"id\";s:32:\"1d996b61ee20735a967752c065fd62b0\";s:5:\"value\";s:8:\"<p>3</p>\";s:4:\"code\";s:1:\"A\";}i:1;a:3:{s:2:\"id\";s:32:\"7667e2cd947e57f259549e120bbc619d\";s:5:\"value\";s:8:\"<p>4</p>\";s:4:\"code\";s:1:\"B\";}i:2;a:3:{s:2:\"id\";s:32:\"d1a89b1335613b7b84b5426e0ef6452a\";s:5:\"value\";s:8:\"<p>2</p>\";s:4:\"code\";s:1:\"C\";}i:3;a:3:{s:2:\"id\";s:32:\"a22d6a95d33b5208f04eedb325282800\";s:5:\"value\";s:8:\"<p>1</p>\";s:4:\"code\";s:1:\"D\";}}}",
        "user_answer": null,
        "correct_answer": "a:4:{i:0;s:32:\"a22d6a95d33b5208f04eedb325282800\";i:1;s:32:\"d1a89b1335613b7b84b5426e0ef6452a\";i:2;s:32:\"1d996b61ee20735a967752c065fd62b0\";i:3;s:32:\"7667e2cd947e57f259549e120bbc619d\";}",
        "status": "not_visited",
        "is_correct": null,
        "time_taken": 0,
        "marks_earned": 0,
        "marks_deducted": 0
    },
    {
        "quiz_session_id": 24,
        "sno": 4,
        "question_id": 3,
        "original_question": "<p>What is the weight of The Sun?</p>",
        "options": "a:4:{i:0;s:10:\"<p>5kg</p>\";i:1;s:10:\"<p>2kg</p>\";i:2;s:10:\"<p>9kg</p>\";i:3;s:21:\"<p>more than 9kg.</p>\";}",
        "user_answer": null,
        "correct_answer": "i:4;",
        "status": "not_visited",
        "is_correct": null,
        "time_taken": 0,
        "marks_earned": 0,
        "marks_deducted": 0
    },
    {
        "quiz_session_id": 24,
        "sno": 5,
        "question_id": 4,
        "original_question": "<p>What is the amount of charge a proton holds?</p>",
        "options": "a:4:{i:0;s:9:\"<p>1e</p>\";i:1;s:9:\"<p>2e</p>\";i:2;s:9:\"<p>3e</p>\";i:3;s:9:\"<p>4e</p>\";}",
        "user_answer": null,
        "correct_answer": "i:1;",
        "status": "not_visited",
        "is_correct": null,
        "time_taken": 0,
        "marks_earned": 0,
        "marks_deducted": 0
    },
    {
        "quiz_session_id": 24,
        "sno": 1,
        "question_id": 5,
        "original_question": "<p>Which of the following is not an electric appliances?</p>",
        "options": "a:4:{i:0;s:25:\"<p>electron projector</p>\";i:1;s:11:\"<p>Bulb</p>\";i:2;s:28:\"<p>Thermonuclear reactor</p>\";i:3;s:10:\"<p>Fan</p>\";}",
        "user_answer": "i:1;",
        "correct_answer": "i:1;",
        "status": "answered",
        "is_correct": 1,
        "time_taken": 15,
        "marks_earned": 30,
        "marks_deducted": 0
    },
    {
        "quiz_session_id": 25,
        "sno": 5,
        "question_id": 1,
        "original_question": "<p>What is the charge of an electron?</p>",
        "options": "a:2:{i:0;s:15:\"<p>Positive</p>\";i:1;s:15:\"<p>Negative</p>\";}",
        "user_answer": "N;",
        "correct_answer": "i:2;",
        "status": "not_answered",
        "is_correct": 0,
        "time_taken": 56,
        "marks_earned": 0,
        "marks_deducted": 0
    },
    {
        "quiz_session_id": 25,
        "sno": 1,
        "question_id": 2,
        "original_question": "<p>What is the order of fundamental forces in nature according to their strengths.</p>",
        "options": "a:2:{s:7:\"matches\";a:4:{i:0;a:2:{s:2:\"id\";s:32:\"c215fc75951b35c5847a807240fab2ea\";s:5:\"value\";s:20:\"<p>Nuclear Force</p>\";}i:1;a:2:{s:2:\"id\";s:32:\"a9577d25b70d4788551133ae4f265347\";s:5:\"value\";s:27:\"<p>Electomagnetic Force</p>\";}i:2;a:2:{s:2:\"id\";s:32:\"2577539023dcd204eb78a3ad1cd6201c\";s:5:\"value\";s:25:\"<p>Weak Nuclear Force</p>\";}i:3;a:2:{s:2:\"id\";s:32:\"19be0e556de5c94f431c8d9ced56641f\";s:5:\"value\";s:26:\"<p>Gravitational Force</p>\";}}s:5:\"pairs\";a:4:{i:0;a:3:{s:2:\"id\";s:32:\"7667e2cd947e57f259549e120bbc619d\";s:5:\"value\";s:8:\"<p>4</p>\";s:4:\"code\";s:1:\"A\";}i:1;a:3:{s:2:\"id\";s:32:\"1d996b61ee20735a967752c065fd62b0\";s:5:\"value\";s:8:\"<p>3</p>\";s:4:\"code\";s:1:\"B\";}i:2;a:3:{s:2:\"id\";s:32:\"d1a89b1335613b7b84b5426e0ef6452a\";s:5:\"value\";s:8:\"<p>2</p>\";s:4:\"code\";s:1:\"C\";}i:3;a:3:{s:2:\"id\";s:32:\"a22d6a95d33b5208f04eedb325282800\";s:5:\"value\";s:8:\"<p>1</p>\";s:4:\"code\";s:1:\"D\";}}}",
        "user_answer": "a:4:{i:0;a:3:{s:2:\"id\";s:32:\"a22d6a95d33b5208f04eedb325282800\";s:5:\"value\";s:8:\"<p>1</p>\";s:4:\"code\";s:1:\"D\";}i:1;a:3:{s:2:\"id\";s:32:\"d1a89b1335613b7b84b5426e0ef6452a\";s:5:\"value\";s:8:\"<p>2</p>\";s:4:\"code\";s:1:\"C\";}i:2;a:3:{s:2:\"id\";s:32:\"1d996b61ee20735a967752c065fd62b0\";s:5:\"value\";s:8:\"<p>3</p>\";s:4:\"code\";s:1:\"B\";}i:3;a:3:{s:2:\"id\";s:32:\"7667e2cd947e57f259549e120bbc619d\";s:5:\"value\";s:8:\"<p>4</p>\";s:4:\"code\";s:1:\"A\";}}",
        "correct_answer": "a:4:{i:0;s:32:\"a22d6a95d33b5208f04eedb325282800\";i:1;s:32:\"d1a89b1335613b7b84b5426e0ef6452a\";i:2;s:32:\"1d996b61ee20735a967752c065fd62b0\";i:3;s:32:\"7667e2cd947e57f259549e120bbc619d\";}",
        "status": "answered",
        "is_correct": 1,
        "time_taken": 22,
        "marks_earned": 300,
        "marks_deducted": 0
    },
    {
        "quiz_session_id": 25,
        "sno": 4,
        "question_id": 3,
        "original_question": "<p>What is the weight of The Sun?</p>",
        "options": "a:4:{i:0;s:10:\"<p>5kg</p>\";i:1;s:10:\"<p>2kg</p>\";i:2;s:10:\"<p>9kg</p>\";i:3;s:21:\"<p>more than 9kg.</p>\";}",
        "user_answer": "i:3;",
        "correct_answer": "i:4;",
        "status": "answered",
        "is_correct": 0,
        "time_taken": 8,
        "marks_earned": 0,
        "marks_deducted": 0
    },
    {
        "quiz_session_id": 25,
        "sno": 2,
        "question_id": 4,
        "original_question": "<p>What is the amount of charge a proton holds?</p>",
        "options": "a:4:{i:0;s:9:\"<p>1e</p>\";i:1;s:9:\"<p>2e</p>\";i:2;s:9:\"<p>3e</p>\";i:3;s:9:\"<p>4e</p>\";}",
        "user_answer": "i:1;",
        "correct_answer": "i:1;",
        "status": "answered",
        "is_correct": 1,
        "time_taken": 8,
        "marks_earned": 30,
        "marks_deducted": 0
    },
    {
        "quiz_session_id": 25,
        "sno": 3,
        "question_id": 5,
        "original_question": "<p>Which of the following is not an electric appliances?</p>",
        "options": "a:4:{i:0;s:25:\"<p>electron projector</p>\";i:1;s:11:\"<p>Bulb</p>\";i:2;s:28:\"<p>Thermonuclear reactor</p>\";i:3;s:10:\"<p>Fan</p>\";}",
        "user_answer": "i:1;",
        "correct_answer": "i:1;",
        "status": "answered",
        "is_correct": 1,
        "time_taken": 14,
        "marks_earned": 30,
        "marks_deducted": 0
    },
    {
        "quiz_session_id": 26,
        "sno": 1,
        "question_id": 1,
        "original_question": "<p>What is the charge of an electron?</p>",
        "options": "a:2:{i:0;s:15:\"<p>Positive</p>\";i:1;s:15:\"<p>Negative</p>\";}",
        "user_answer": "i:2;",
        "correct_answer": "i:2;",
        "status": "answered",
        "is_correct": 1,
        "time_taken": 11,
        "marks_earned": 300,
        "marks_deducted": 0
    },
    {
        "quiz_session_id": 26,
        "sno": 2,
        "question_id": 3,
        "original_question": "<p>What is the weight of The Sun?</p>",
        "options": "a:4:{i:0;s:10:\"<p>5kg</p>\";i:1;s:10:\"<p>2kg</p>\";i:2;s:10:\"<p>9kg</p>\";i:3;s:21:\"<p>more than 9kg.</p>\";}",
        "user_answer": null,
        "correct_answer": "i:4;",
        "status": "not_visited",
        "is_correct": null,
        "time_taken": 0,
        "marks_earned": 0,
        "marks_deducted": 0
    },
    {
        "quiz_session_id": 26,
        "sno": 3,
        "question_id": 4,
        "original_question": "<p>What is the amount of charge a proton holds?</p>",
        "options": "a:4:{i:0;s:9:\"<p>1e</p>\";i:1;s:9:\"<p>2e</p>\";i:2;s:9:\"<p>3e</p>\";i:3;s:9:\"<p>4e</p>\";}",
        "user_answer": "i:1;",
        "correct_answer": "i:1;",
        "status": "answered",
        "is_correct": 1,
        "time_taken": 3,
        "marks_earned": 30,
        "marks_deducted": 0
    },
    {
        "quiz_session_id": 26,
        "sno": 4,
        "question_id": 5,
        "original_question": "<p>Which of the following is not an electric appliances?</p>",
        "options": "a:4:{i:0;s:25:\"<p>electron projector</p>\";i:1;s:11:\"<p>Bulb</p>\";i:2;s:28:\"<p>Thermonuclear reactor</p>\";i:3;s:10:\"<p>Fan</p>\";}",
        "user_answer": "i:2;",
        "correct_answer": "i:1;",
        "status": "answered",
        "is_correct": 0,
        "time_taken": 48,
        "marks_earned": 0,
        "marks_deducted": 0
    },
    {
        "quiz_session_id": 27,
        "sno": 4,
        "question_id": 1,
        "original_question": "<p>What is the charge of an electron?</p>",
        "options": "a:2:{i:0;s:15:\"<p>Positive</p>\";i:1;s:15:\"<p>Negative</p>\";}",
        "user_answer": null,
        "correct_answer": "i:2;",
        "status": "not_visited",
        "is_correct": null,
        "time_taken": 0,
        "marks_earned": 0,
        "marks_deducted": 0
    },
    {
        "quiz_session_id": 27,
        "sno": 3,
        "question_id": 3,
        "original_question": "<p>What is the weight of The Sun?</p>",
        "options": "a:4:{i:0;s:10:\"<p>5kg</p>\";i:1;s:10:\"<p>2kg</p>\";i:2;s:10:\"<p>9kg</p>\";i:3;s:21:\"<p>more than 9kg.</p>\";}",
        "user_answer": "i:3;",
        "correct_answer": "i:4;",
        "status": "answered",
        "is_correct": 0,
        "time_taken": 4,
        "marks_earned": 0,
        "marks_deducted": 0
    },
    {
        "quiz_session_id": 27,
        "sno": 1,
        "question_id": 4,
        "original_question": "<p>What is the amount of charge a proton holds?</p>",
        "options": "a:4:{i:0;s:9:\"<p>1e</p>\";i:1;s:9:\"<p>2e</p>\";i:2;s:9:\"<p>3e</p>\";i:3;s:9:\"<p>4e</p>\";}",
        "user_answer": "i:3;",
        "correct_answer": "i:1;",
        "status": "answered",
        "is_correct": 0,
        "time_taken": 13,
        "marks_earned": 0,
        "marks_deducted": 0
    },
    {
        "quiz_session_id": 27,
        "sno": 2,
        "question_id": 5,
        "original_question": "<p>Which of the following is not an electric appliances?</p>",
        "options": "a:4:{i:0;s:25:\"<p>electron projector</p>\";i:1;s:11:\"<p>Bulb</p>\";i:2;s:28:\"<p>Thermonuclear reactor</p>\";i:3;s:10:\"<p>Fan</p>\";}",
        "user_answer": "i:2;",
        "correct_answer": "i:1;",
        "status": "answered",
        "is_correct": 0,
        "time_taken": 12,
        "marks_earned": 0,
        "marks_deducted": 0
    },
    {
        "quiz_session_id": 28,
        "sno": 4,
        "question_id": 1,
        "original_question": "<p>What is the charge of an electron?</p>",
        "options": "a:2:{i:0;s:15:\"<p>Positive</p>\";i:1;s:15:\"<p>Negative</p>\";}",
        "user_answer": "i:1;",
        "correct_answer": "i:2;",
        "status": "answered",
        "is_correct": 0,
        "time_taken": 11,
        "marks_earned": 0,
        "marks_deducted": 0
    },
    {
        "quiz_session_id": 28,
        "sno": 1,
        "question_id": 3,
        "original_question": "<p>What is the weight of The Sun?</p>",
        "options": "a:4:{i:0;s:10:\"<p>5kg</p>\";i:1;s:10:\"<p>2kg</p>\";i:2;s:10:\"<p>9kg</p>\";i:3;s:21:\"<p>more than 9kg.</p>\";}",
        "user_answer": "i:3;",
        "correct_answer": "i:4;",
        "status": "answered",
        "is_correct": 0,
        "time_taken": 5,
        "marks_earned": 0,
        "marks_deducted": 0
    },
    {
        "quiz_session_id": 28,
        "sno": 2,
        "question_id": 4,
        "original_question": "<p>What is the amount of charge a proton holds?</p>",
        "options": "a:4:{i:0;s:9:\"<p>1e</p>\";i:1;s:9:\"<p>2e</p>\";i:2;s:9:\"<p>3e</p>\";i:3;s:9:\"<p>4e</p>\";}",
        "user_answer": "i:1;",
        "correct_answer": "i:1;",
        "status": "answered",
        "is_correct": 1,
        "time_taken": 5,
        "marks_earned": 30,
        "marks_deducted": 0
    },
    {
        "quiz_session_id": 28,
        "sno": 3,
        "question_id": 5,
        "original_question": "<p>Which of the following is not an electric appliances?</p>",
        "options": "a:4:{i:0;s:25:\"<p>electron projector</p>\";i:1;s:11:\"<p>Bulb</p>\";i:2;s:28:\"<p>Thermonuclear reactor</p>\";i:3;s:10:\"<p>Fan</p>\";}",
        "user_answer": "i:1;",
        "correct_answer": "i:1;",
        "status": "answered",
        "is_correct": 1,
        "time_taken": 4,
        "marks_earned": 30,
        "marks_deducted": 0
    },
    {
        "quiz_session_id": 29,
        "sno": 3,
        "question_id": 3,
        "original_question": "<p>What is the weight of The Sun?</p>",
        "options": "a:4:{i:0;s:10:\"<p>5kg</p>\";i:1;s:10:\"<p>2kg</p>\";i:2;s:10:\"<p>9kg</p>\";i:3;s:21:\"<p>more than 9kg.</p>\";}",
        "user_answer": "i:4;",
        "correct_answer": "i:4;",
        "status": "answered",
        "is_correct": 1,
        "time_taken": 8,
        "marks_earned": 30,
        "marks_deducted": 0
    },
    {
        "quiz_session_id": 29,
        "sno": 1,
        "question_id": 4,
        "original_question": "<p>What is the amount of charge a proton holds?</p>",
        "options": "a:4:{i:0;s:9:\"<p>1e</p>\";i:1;s:9:\"<p>2e</p>\";i:2;s:9:\"<p>3e</p>\";i:3;s:9:\"<p>4e</p>\";}",
        "user_answer": "i:2;",
        "correct_answer": "i:1;",
        "status": "answered",
        "is_correct": 0,
        "time_taken": 4,
        "marks_earned": 0,
        "marks_deducted": 0
    },
    {
        "quiz_session_id": 29,
        "sno": 2,
        "question_id": 5,
        "original_question": "<p>Which of the following is not an electric appliances?</p>",
        "options": "a:4:{i:0;s:25:\"<p>electron projector</p>\";i:1;s:11:\"<p>Bulb</p>\";i:2;s:28:\"<p>Thermonuclear reactor</p>\";i:3;s:10:\"<p>Fan</p>\";}",
        "user_answer": "i:1;",
        "correct_answer": "i:1;",
        "status": "answered",
        "is_correct": 1,
        "time_taken": 4,
        "marks_earned": 30,
        "marks_deducted": 0
    },
    {
        "quiz_session_id": 30,
        "sno": 1,
        "question_id": 3,
        "original_question": "<p>What is the weight of The Sun?</p>",
        "options": "a:4:{i:0;s:10:\"<p>5kg</p>\";i:1;s:10:\"<p>2kg</p>\";i:2;s:10:\"<p>9kg</p>\";i:3;s:21:\"<p>more than 9kg.</p>\";}",
        "user_answer": "i:4;",
        "correct_answer": "i:4;",
        "status": "answered",
        "is_correct": 1,
        "time_taken": 3,
        "marks_earned": 30,
        "marks_deducted": 0
    },
    {
        "quiz_session_id": 30,
        "sno": 2,
        "question_id": 4,
        "original_question": "<p>What is the amount of charge a proton holds?</p>",
        "options": "a:4:{i:0;s:9:\"<p>1e</p>\";i:1;s:9:\"<p>2e</p>\";i:2;s:9:\"<p>3e</p>\";i:3;s:9:\"<p>4e</p>\";}",
        "user_answer": "i:1;",
        "correct_answer": "i:1;",
        "status": "answered",
        "is_correct": 1,
        "time_taken": 5,
        "marks_earned": 30,
        "marks_deducted": 0
    },
    {
        "quiz_session_id": 30,
        "sno": 3,
        "question_id": 5,
        "original_question": "<p>Which of the following is not an electric appliances?</p>",
        "options": "a:4:{i:0;s:25:\"<p>electron projector</p>\";i:1;s:11:\"<p>Bulb</p>\";i:2;s:28:\"<p>Thermonuclear reactor</p>\";i:3;s:10:\"<p>Fan</p>\";}",
        "user_answer": "N;",
        "correct_answer": "i:1;",
        "status": "not_answered",
        "is_correct": 0,
        "time_taken": 3,
        "marks_earned": 0,
        "marks_deducted": 0
    },
    {
        "quiz_session_id": 31,
        "sno": 2,
        "question_id": 3,
        "original_question": "<p>What is the weight of The Sun?</p>",
        "options": "a:4:{i:0;s:10:\"<p>5kg</p>\";i:1;s:10:\"<p>2kg</p>\";i:2;s:10:\"<p>9kg</p>\";i:3;s:21:\"<p>more than 9kg.</p>\";}",
        "user_answer": "i:2;",
        "correct_answer": "i:4;",
        "status": "answered",
        "is_correct": 0,
        "time_taken": 3,
        "marks_earned": 0,
        "marks_deducted": 0
    },
    {
        "quiz_session_id": 31,
        "sno": 3,
        "question_id": 4,
        "original_question": "<p>What is the amount of charge a proton holds?</p>",
        "options": "a:4:{i:0;s:9:\"<p>1e</p>\";i:1;s:9:\"<p>2e</p>\";i:2;s:9:\"<p>3e</p>\";i:3;s:9:\"<p>4e</p>\";}",
        "user_answer": "i:2;",
        "correct_answer": "i:1;",
        "status": "answered",
        "is_correct": 0,
        "time_taken": 8,
        "marks_earned": 0,
        "marks_deducted": 0
    },
    {
        "quiz_session_id": 31,
        "sno": 1,
        "question_id": 5,
        "original_question": "<p>Which of the following is not an electric appliances?</p>",
        "options": "a:4:{i:0;s:25:\"<p>electron projector</p>\";i:1;s:11:\"<p>Bulb</p>\";i:2;s:28:\"<p>Thermonuclear reactor</p>\";i:3;s:10:\"<p>Fan</p>\";}",
        "user_answer": "i:1;",
        "correct_answer": "i:1;",
        "status": "answered",
        "is_correct": 1,
        "time_taken": 3,
        "marks_earned": 30,
        "marks_deducted": 0
    },
    {
        "quiz_session_id": 32,
        "sno": 3,
        "question_id": 3,
        "original_question": "<p>What is the weight of The Sun?</p>",
        "options": "a:4:{i:0;s:10:\"<p>5kg</p>\";i:1;s:10:\"<p>2kg</p>\";i:2;s:10:\"<p>9kg</p>\";i:3;s:21:\"<p>more than 9kg.</p>\";}",
        "user_answer": null,
        "correct_answer": "i:4;",
        "status": "not_visited",
        "is_correct": null,
        "time_taken": 0,
        "marks_earned": 0,
        "marks_deducted": 0
    },
    {
        "quiz_session_id": 32,
        "sno": 1,
        "question_id": 4,
        "original_question": "<p>What is the amount of charge a proton holds?</p>",
        "options": "a:4:{i:0;s:9:\"<p>1e</p>\";i:1;s:9:\"<p>2e</p>\";i:2;s:9:\"<p>3e</p>\";i:3;s:9:\"<p>4e</p>\";}",
        "user_answer": "i:1;",
        "correct_answer": "i:1;",
        "status": "answered",
        "is_correct": 1,
        "time_taken": 3,
        "marks_earned": 30,
        "marks_deducted": 0
    },
    {
        "quiz_session_id": 32,
        "sno": 2,
        "question_id": 5,
        "original_question": "<p>Which of the following is not an electric appliances?</p>",
        "options": "a:4:{i:0;s:25:\"<p>electron projector</p>\";i:1;s:11:\"<p>Bulb</p>\";i:2;s:28:\"<p>Thermonuclear reactor</p>\";i:3;s:10:\"<p>Fan</p>\";}",
        "user_answer": "i:2;",
        "correct_answer": "i:1;",
        "status": "answered",
        "is_correct": 0,
        "time_taken": 3,
        "marks_earned": 0,
        "marks_deducted": 0
    },
    {
        "quiz_session_id": 33,
        "sno": 1,
        "question_id": 3,
        "original_question": "<p>What is the weight of The Sun?</p>",
        "options": "a:4:{i:0;s:10:\"<p>5kg</p>\";i:1;s:10:\"<p>2kg</p>\";i:2;s:10:\"<p>9kg</p>\";i:3;s:21:\"<p>more than 9kg.</p>\";}",
        "user_answer": "i:4;",
        "correct_answer": "i:4;",
        "status": "answered",
        "is_correct": 1,
        "time_taken": 2,
        "marks_earned": 28,
        "marks_deducted": 0
    },
    {
        "quiz_session_id": 33,
        "sno": 2,
        "question_id": 4,
        "original_question": "<p>What is the amount of charge a proton holds?</p>",
        "options": "a:4:{i:0;s:9:\"<p>1e</p>\";i:1;s:9:\"<p>2e</p>\";i:2;s:9:\"<p>3e</p>\";i:3;s:9:\"<p>4e</p>\";}",
        "user_answer": "i:1;",
        "correct_answer": "i:1;",
        "status": "answered",
        "is_correct": 1,
        "time_taken": 3,
        "marks_earned": 28,
        "marks_deducted": 0
    },
    {
        "quiz_session_id": 33,
        "sno": 3,
        "question_id": 5,
        "original_question": "<p>Which of the following is not an electric appliances?</p>",
        "options": "a:4:{i:0;s:25:\"<p>electron projector</p>\";i:1;s:11:\"<p>Bulb</p>\";i:2;s:28:\"<p>Thermonuclear reactor</p>\";i:3;s:10:\"<p>Fan</p>\";}",
        "user_answer": "i:2;",
        "correct_answer": "i:1;",
        "status": "answered",
        "is_correct": 0,
        "time_taken": 5,
        "marks_earned": 0,
        "marks_deducted": 0
    },
    {
        "quiz_session_id": 34,
        "sno": 3,
        "question_id": 3,
        "original_question": "<p>What is the weight of The Sun?</p>",
        "options": "a:4:{i:0;s:10:\"<p>5kg</p>\";i:1;s:10:\"<p>2kg</p>\";i:2;s:10:\"<p>9kg</p>\";i:3;s:21:\"<p>more than 9kg.</p>\";}",
        "user_answer": "i:3;",
        "correct_answer": "i:4;",
        "status": "answered",
        "is_correct": 0,
        "time_taken": 4,
        "marks_earned": 0,
        "marks_deducted": 0
    },
    {
        "quiz_session_id": 34,
        "sno": 2,
        "question_id": 4,
        "original_question": "<p>What is the amount of charge a proton holds?</p>",
        "options": "a:4:{i:0;s:9:\"<p>1e</p>\";i:1;s:9:\"<p>2e</p>\";i:2;s:9:\"<p>3e</p>\";i:3;s:9:\"<p>4e</p>\";}",
        "user_answer": "i:1;",
        "correct_answer": "i:1;",
        "status": "answered",
        "is_correct": 1,
        "time_taken": 3,
        "marks_earned": 27,
        "marks_deducted": 0
    },
    {
        "quiz_session_id": 34,
        "sno": 1,
        "question_id": 5,
        "original_question": "<p>Which of the following is not an electric appliances?</p>",
        "options": "a:4:{i:0;s:25:\"<p>electron projector</p>\";i:1;s:11:\"<p>Bulb</p>\";i:2;s:28:\"<p>Thermonuclear reactor</p>\";i:3;s:10:\"<p>Fan</p>\";}",
        "user_answer": "i:1;",
        "correct_answer": "i:1;",
        "status": "answered",
        "is_correct": 1,
        "time_taken": 5,
        "marks_earned": 25,
        "marks_deducted": 0
    },
    {
        "quiz_session_id": 35,
        "sno": 1,
        "question_id": 3,
        "original_question": "<p>What is the weight of The Sun?</p>",
        "options": "a:4:{i:0;s:10:\"<p>5kg</p>\";i:1;s:10:\"<p>2kg</p>\";i:2;s:10:\"<p>9kg</p>\";i:3;s:21:\"<p>more than 9kg.</p>\";}",
        "user_answer": "N;",
        "correct_answer": "i:4;",
        "status": "not_answered",
        "is_correct": 0,
        "time_taken": 3,
        "marks_earned": 0,
        "marks_deducted": 0
    },
    {
        "quiz_session_id": 35,
        "sno": 3,
        "question_id": 4,
        "original_question": "<p>What is the amount of charge a proton holds?</p>",
        "options": "a:4:{i:0;s:9:\"<p>1e</p>\";i:1;s:9:\"<p>2e</p>\";i:2;s:9:\"<p>3e</p>\";i:3;s:9:\"<p>4e</p>\";}",
        "user_answer": null,
        "correct_answer": "i:1;",
        "status": "not_visited",
        "is_correct": null,
        "time_taken": 0,
        "marks_earned": 0,
        "marks_deducted": 0
    },
    {
        "quiz_session_id": 35,
        "sno": 2,
        "question_id": 5,
        "original_question": "<p>Which of the following is not an electric appliances?</p>",
        "options": "a:4:{i:0;s:25:\"<p>electron projector</p>\";i:1;s:11:\"<p>Bulb</p>\";i:2;s:28:\"<p>Thermonuclear reactor</p>\";i:3;s:10:\"<p>Fan</p>\";}",
        "user_answer": null,
        "correct_answer": "i:1;",
        "status": "not_visited",
        "is_correct": null,
        "time_taken": 0,
        "marks_earned": 0,
        "marks_deducted": 0
    }
]
